chattie/__init__.py
chattie/bot.py
chattie/cli.py
chattie/plugins.py
chattie/connectors/__init__.py
chattie/connectors/matrix.py
chattie/connectors/telegram.py
chattie/connectors/term.py
chattie/inventory/__init__.py
chattie/inventory/json.py
chattie/tricks/__init__.py
chattie-0.2.1.dist-info/DESCRIPTION.rst
chattie-0.2.1.dist-info/METADATA
chattie-0.2.1.dist-info/RECORD
chattie-0.2.1.dist-info/WHEEL
chattie-0.2.1.dist-info/entry_points.txt
chattie-0.2.1.dist-info/metadata.json
chattie-0.2.1.dist-info/top_level.txt
