Metadata-Version: 2.0
Name: chattie
Version: 0.2.1
Summary: A framework for making bots in Python. Inspired by Hubot
Home-page: UNKNOWN
Author: Mathew Robinson
Author-email: mrobinson@praelatus.io
License: Apache2.0
Download-URL: https://github.com/chasinglogic/Chattie
Platform: UNKNOWN
Classifier: License :: OSI Approved :: Apache Software License
Classifier: Programming Language :: Python :: 3
Requires-Dist: requests
Requires-Dist: click
Provides-Extra: matrix
Requires-Dist: matrix-client; extra == 'matrix'
Provides-Extra: telegram
Requires-Dist: telegram; extra == 'telegram'
